tornado_profile.py
tornado_profile-1.2.0.dist-info/DESCRIPTION.rst
tornado_profile-1.2.0.dist-info/METADATA
tornado_profile-1.2.0.dist-info/RECORD
tornado_profile-1.2.0.dist-info/WHEEL
tornado_profile-1.2.0.dist-info/metadata.json
tornado_profile-1.2.0.dist-info/top_level.txt
