Metadata-Version: 2.0
Name: tornado-profile
Version: 1.2.0
Summary: Profile a Tornado application via REST
Home-page: https://github.com/makearl/tornado-profile
Author: Megan Kearl Patten
Author-email: megkearl@gmail.com
License: MIT
Keywords: tornado profile profiler rest
Platform: UNKNOWN
Classifier: Programming Language :: Python :: 2
Classifier: Intended Audience :: Developers
Classifier: License :: OSI Approved :: MIT License
Classifier: Topic :: Utilities
Requires-Dist: tornado
Requires-Dist: yappi
